jweb/img/app.py
jweb/img/templates/2side_comp.html
jweb/img/templates/folder.html
jweb/utils/__init__.py
jweb/utils/files.py
jweb-0.0.5.dist-info/METADATA
jweb-0.0.5.dist-info/WHEEL
jweb-0.0.5.dist-info/entry_points.txt
jweb-0.0.5.dist-info/RECORD
